surround_cli/__init__.py
surround_cli/cli.py
surround_cli/linter.py
surround_cli/split_data.py
surround_cli/checkers/__init__.py
surround_cli/checkers/surround_checker.py
surround_cli/data/__init__.py
surround_cli/data/container.py
surround_cli/data/linter.py
surround_cli/data/metadata.py
surround_cli/data/util.py
surround_cli/data/cli/__init__.py
surround_cli/data/cli/cli.py
surround_cli/data/cli/create.py
surround_cli/data/cli/inspect.py
surround_cli/data/cli/lint.py
surround_cli/remote/__init__.py
surround_cli/remote/base.py
surround_cli/remote/cli.py
surround_cli/remote/local.py
surround_cli/split/cli.py
surround_cli/split/split_data.py
surround_cli/visualise/cli.py
surround_cli/visualise/visualise_classifier.py
surround_cli/visualise/visualise_classifier_template.html.txt
templates/new/.gitignore.txt
templates/new/Dockerfile.Notebook.txt
templates/new/Dockerfile.txt
templates/new/README.md.txt
templates/new/VERSION.txt
templates/new/assembler_state.py.txt
templates/new/baseline.py.txt
templates/new/batch_main.py.txt
templates/new/config.py.txt
templates/new/config.yaml.txt
templates/new/data_analysis.ipynb.txt
templates/new/dodo.py.txt
templates/new/file_system_runner.py.txt
templates/new/init.py.txt
templates/new/input_validator.py.txt
templates/new/stages_init.py.txt
templates/new/web_dodo.py.txt
templates/new/web_main.py.txt
templates/new/web_runner.py.txt
surround_cli-0.0.5.dist-info/METADATA
surround_cli-0.0.5.dist-info/WHEEL
surround_cli-0.0.5.dist-info/entry_points.txt
surround_cli-0.0.5.dist-info/top_level.txt
surround_cli-0.0.5.dist-info/RECORD
