Metadata-Version: 2.1
Name: surround-cli
Version: 0.0.5
Summary: Command line interface for Surround
Home-page: https://github.com/a2i2/surround
Author: Scott Barnett
Author-email: scott.barnett@deakin.edu.au
License: BSD-3-Clause License
Platform: UNKNOWN
Requires-Dist: numpy (==1.17.3)
Requires-Dist: pandas (==0.25.2)
Requires-Dist: doit (==0.31.1)
Requires-Dist: tornado (==6.1.0)
Requires-Dist: pylint (==2.4.3)
Requires-Dist: surround (==0.1.2)
